zgw_consumers_oas/__init__.py
zgw_consumers_oas/component_generation.py
zgw_consumers_oas/mocks.py
zgw_consumers_oas/py.typed
zgw_consumers_oas/schema_loading.py
zgw_consumers_oas/settings.py
zgw_consumers_oas-1.1.0.dist-info/licenses/LICENSE
zgw_consumers_oas-1.1.0.dist-info/METADATA
zgw_consumers_oas-1.1.0.dist-info/WHEEL
zgw_consumers_oas-1.1.0.dist-info/top_level.txt
zgw_consumers_oas-1.1.0.dist-info/RECORD
