Metadata-Version: 2.4
Name: zgw-consumers-oas
Version: 1.1.0
Summary: Tooling to deal with OpenAPI specifications, extracted from zgw-consumers.
Author-email: Maykin Media <support@maykinmedia.nl>
License: Copyright 2024 Maykin Media
Project-URL: Homepage, https://github.com/maykinmedia/zgw-consumers-oas
Project-URL: Bug Tracker, https://github.com/maykinmedia/zgw-consumers-oas/issues
Project-URL: Source Code, https://github.com/maykinmedia/zgw-consumers-oas
Keywords: Django,ZGW,Common Ground,VNG,API,OpenAPI,OAS,mTLS
Classifier: Development Status :: 5 - Production/Stable
Classifier: Framework :: Django
Classifier: Framework :: Django :: 3.2
Classifier: Framework :: Django :: 4.2
Classifier: Intended Audience :: Developers
Classifier: Operating System :: Unix
Classifier: Operating System :: MacOS
Classifier: Operating System :: Microsoft :: Windows
Classifier: Programming Language :: Python :: 3.10
Classifier: Programming Language :: Python :: 3.11
Classifier: Programming Language :: Python :: 3.12
Classifier: Topic :: Software Development :: Libraries :: Python Modules
Requires-Python: >=3.10
License-File: LICENSE
Requires-Dist: django>=3.2
Requires-Dist: typing_extensions>=4.5.0
Requires-Dist: Faker>=0.7.0
Requires-Dist: pyyaml
Provides-Extra: mocks
Requires-Dist: requests-mock; extra == "mocks"
Provides-Extra: tests
Requires-Dist: pytest; extra == "tests"
Requires-Dist: pytest-django; extra == "tests"
Requires-Dist: tox; extra == "tests"
Requires-Dist: isort; extra == "tests"
Requires-Dist: black; extra == "tests"
Requires-Dist: flake8; extra == "tests"
Provides-Extra: coverage
Requires-Dist: pytest-cov; extra == "coverage"
Provides-Extra: release
Requires-Dist: bump-my-version; extra == "release"
Dynamic: license-file
